zim_anything/__init__.py
zim_anything/automatic_mask_generator.py
zim_anything/build_model.py
zim_anything/predictor.py
zim_anything/modeling/__init__.py
zim_anything/modeling/decoder.py
zim_anything/modeling/encoder.py
zim_anything/modeling/zim.py
zim_anything/utils/__init__.py
zim_anything/utils/amg.py
zim_anything/utils/argparser.py
zim_anything/utils/print.py
zim_anything/utils/utils.py
zim_config/__init__.py
zim_config/config.py
zim_anything-0.1.dist-info/LICENSE
zim_anything-0.1.dist-info/METADATA
zim_anything-0.1.dist-info/NOTICE
zim_anything-0.1.dist-info/WHEEL
zim_anything-0.1.dist-info/top_level.txt
zim_anything-0.1.dist-info/RECORD
