Metadata-Version: 2.1
Name: zim_anything
Version: 0.1
License-File: LICENSE
License-File: NOTICE
Requires-Dist: onnx
Requires-Dist: onnxruntime-gpu
Provides-Extra: all
Requires-Dist: matplotlib ; extra == 'all'
Requires-Dist: pycocotools ; extra == 'all'
Requires-Dist: opencv-python ; extra == 'all'
Provides-Extra: dev
Requires-Dist: flake8 ; extra == 'dev'
Requires-Dist: isort ; extra == 'dev'
Requires-Dist: black ; extra == 'dev'
Requires-Dist: mypy ; extra == 'dev'
